accel/__init__.py
accel/__main__.py
accel/base/__init__.py
accel/base/atoms.py
accel/base/box.py
accel/base/boxcore.py
accel/base/formats.py
accel/base/modeler.py
accel/base/selector.py
accel/base/systems.py
accel/base/tools.py
accel/base/topology.py
accel/plugin/__init__.py
accel/plugin/gaulib.py
accel/plugin/maelib.py
accel/plugin/orclib.py
accel/plugin/pbslib.py
accel/plugin/txtlib.py
accel/plugin/xtblib.py
accel/util/__init__.py
accel/util/constants.py
accel/util/datadict.py
accel/util/dialog.py
accel/util/dialogue.py
accel/util/elements.pkl
accel/util/execmd.py
accel/util/filetype.py
accel/util/log.py
accel/util/logo32.png
accel/util/matrix.py
accel-0.3.0.dist-info/LICENSE
accel-0.3.0.dist-info/METADATA
accel-0.3.0.dist-info/WHEEL
accel-0.3.0.dist-info/top_level.txt
accel-0.3.0.dist-info/RECORD
