Metadata-Version: 2.1
Name: accel
Version: 0.3.0
Summary: ACCeL is a Python package for managing and filtering conformers in computational chemistry.
Home-page: https://github.com/kfchem/accel
Author: Keisuke Fukaya
Author-email: kfukaya@pu-toyama.ac.jp
License: MIT License
Platform: UNKNOWN
Classifier: Programming Language :: Python :: 3
Classifier: License :: OSI Approved :: MIT License
Classifier: Operating System :: OS Independent
Requires-Python: >=3.9
License-File: LICENSE
Requires-Dist: numpy
